repoet/__init__.py
repoet/op.py
repoet/pattern.py
repoet/pattern.pyi
repoet/py.typed
repoet-0.1.2.dist-info/LICENSE
repoet-0.1.2.dist-info/METADATA
repoet-0.1.2.dist-info/WHEEL
repoet-0.1.2.dist-info/top_level.txt
repoet-0.1.2.dist-info/RECORD
