Metadata-Version: 2.1
Name: repoet
Version: 0.1.2
Summary: Write regular expressions like poetry in Python - transform cryptic regex into elegant, readable patterns
Home-page: https://github.com/Dawnfz-Lenfeng/repoet
Author: Dawnfz-Lenfeng
Author-email: 2912706234@qq.com
License: MIT
Project-URL: Bug Tracker, https://github.com/Dawnfz-Lenfeng/repoet/issues
Keywords: regex,regular expression,pattern matching,readable
Classifier: Development Status :: 3 - Alpha
Classifier: Intended Audience :: Developers
Classifier: License :: OSI Approved :: MIT License
Classifier: Programming Language :: Python :: 3
Classifier: Programming Language :: Python :: 3.7
Classifier: Programming Language :: Python :: 3.8
Classifier: Programming Language :: Python :: 3.9
Classifier: Programming Language :: Python :: 3.10
Classifier: Programming Language :: Python :: 3.11
Classifier: Topic :: Software Development :: Libraries :: Python Modules
Classifier: Topic :: Text Processing :: General
Requires-Python: >=3.7
License-File: LICENSE
Requires-Dist: typing-extensions>=4.0.0; python_version < "3.8"
Provides-Extra: dev
Requires-Dist: pytest>=6.0; extra == "dev"
Requires-Dist: pytest-cov>=2.0; extra == "dev"
Requires-Dist: black>=22.0; extra == "dev"
Requires-Dist: isort>=5.0; extra == "dev"
Requires-Dist: mypy>=0.900; extra == "dev"
Requires-Dist: flake8>=3.9; extra == "dev"
Requires-Dist: tox>=3.24; extra == "dev"
Provides-Extra: docs
Requires-Dist: sphinx>=4.0; extra == "docs"
Requires-Dist: sphinx-rtd-theme>=0.5; extra == "docs"
